roboswag/__init__.py
roboswag/__main__.py
roboswag/auth.py
roboswag/cli.py
roboswag/core.py
roboswag/generate/__init__.py
roboswag/generate/generate.py
roboswag/generate/models/__init__.py
roboswag/generate/models/api.py
roboswag/generate/models/definition.py
roboswag/generate/models/endpoint.py
roboswag/generate/models/parameter.py
roboswag/generate/models/response.py
roboswag/generate/models/tag.py
roboswag/generate/models/utils.py
roboswag/generate/templates/api_init.jinja
roboswag/generate/templates/models.jinja
roboswag/generate/templates/paths.jinja
roboswag/logger.py
roboswag/validate/__init__.py
roboswag/validate/core.py
roboswag/validate/schema.py
roboswag/validate/text_response.py
roboswag/version.py
roboswag-0.4.0.dist-info/entry_points.txt
roboswag-0.4.0.dist-info/LICENSE
roboswag-0.4.0.dist-info/WHEEL
roboswag-0.4.0.dist-info/METADATA
roboswag-0.4.0.dist-info/RECORD
