Metadata-Version: 2.1
Name: roboswag
Version: 0.4.0
Summary: Test framework for auto-generating libraries from OpenAPI specification file.
Home-page: https://pypi.org/project/roboswag
License: Apache-2.0
Keywords: testing,api,testautomation,openapi,robotframework
Author: Mateusz Nojek
Author-email: matnojek@gmail.com
Requires-Python: >=3.7,<4.0
Classifier: Development Status :: 3 - Alpha
Classifier: Framework :: Robot Framework
Classifier: Framework :: Robot Framework :: Tool
Classifier: Intended Audience :: Developers
Classifier: License :: OSI Approved :: Apache Software License
Classifier: Operating System :: OS Independent
Classifier: Programming Language :: Python
Classifier: Programming Language :: Python :: 3
Classifier: Programming Language :: Python :: 3.10
Classifier: Programming Language :: Python :: 3.7
Classifier: Programming Language :: Python :: 3.8
Classifier: Programming Language :: Python :: 3.9
Classifier: Topic :: Software Development :: Quality Assurance
Classifier: Topic :: Software Development :: Testing
Classifier: Topic :: Utilities
Requires-Dist: Jinja2 (>=3.1.2,<4.0.0)
Requires-Dist: PyYAML (>=6.0,<7.0)
Requires-Dist: black (>=22.3.0,<23.0.0)
Requires-Dist: click (>=8.1.0)
Requires-Dist: jsonschema (>=4.5.1,<5.0.0)
Requires-Dist: openapi-spec-validator (>=0.4.0,<0.5.0)
Requires-Dist: prance (>=0.21.8,<0.22.0)
Requires-Dist: requests (>=2.27.1,<3.0.0)
Requires-Dist: rich_click (>=1.4,<2.0)
Requires-Dist: robotframework (>=4.1)
Requires-Dist: urllib3 (>=1.26.9,<2.0.0)
Project-URL: Repository, https://github.com/MarketSquare/roboswag
